opensesame_extensions/osweb/__init__.py
opensesame_extensions/osweb/oswebext/__init__.py
opensesame_extensions/osweb/oswebext/locale/ar.qm
opensesame_extensions/osweb/oswebext/locale/ar.ts
opensesame_extensions/osweb/oswebext/locale/bn.qm
opensesame_extensions/osweb/oswebext/locale/bn.ts
opensesame_extensions/osweb/oswebext/locale/de.qm
opensesame_extensions/osweb/oswebext/locale/de.ts
opensesame_extensions/osweb/oswebext/locale/es.qm
opensesame_extensions/osweb/oswebext/locale/es.ts
opensesame_extensions/osweb/oswebext/locale/fr.qm
opensesame_extensions/osweb/oswebext/locale/fr.ts
opensesame_extensions/osweb/oswebext/locale/he.qm
opensesame_extensions/osweb/oswebext/locale/he.ts
opensesame_extensions/osweb/oswebext/locale/hi.qm
opensesame_extensions/osweb/oswebext/locale/hi.ts
opensesame_extensions/osweb/oswebext/locale/id.qm
opensesame_extensions/osweb/oswebext/locale/id.ts
opensesame_extensions/osweb/oswebext/locale/it.qm
opensesame_extensions/osweb/oswebext/locale/it.ts
opensesame_extensions/osweb/oswebext/locale/ja.qm
opensesame_extensions/osweb/oswebext/locale/ja.ts
opensesame_extensions/osweb/oswebext/locale/ko.qm
opensesame_extensions/osweb/oswebext/locale/ko.ts
opensesame_extensions/osweb/oswebext/locale/nl.qm
opensesame_extensions/osweb/oswebext/locale/nl.ts
opensesame_extensions/osweb/oswebext/locale/pt.qm
opensesame_extensions/osweb/oswebext/locale/pt.ts
opensesame_extensions/osweb/oswebext/locale/ru.qm
opensesame_extensions/osweb/oswebext/locale/ru.ts
opensesame_extensions/osweb/oswebext/locale/tr.qm
opensesame_extensions/osweb/oswebext/locale/tr.ts
opensesame_extensions/osweb/oswebext/locale/translatables.ts
opensesame_extensions/osweb/oswebext/locale/yue.qm
opensesame_extensions/osweb/oswebext/locale/yue.ts
opensesame_extensions/osweb/oswebext/locale/zh.qm
opensesame_extensions/osweb/oswebext/locale/zh.ts
opensesame_extensions/osweb/oswebext/osweb_control_panel.py
opensesame_extensions/osweb/oswebext/osweb_control_panel.ui
opensesame_extension_osweb-2.2.8.0.dist-info/METADATA
opensesame_extension_osweb-2.2.8.0.dist-info/WHEEL
opensesame_extension_osweb-2.2.8.0.dist-info/licenses/COPYING
opensesame_extension_osweb-2.2.8.0.dist-info/RECORD
