Metadata-Version: 2.4
Name: opensesame-extension-osweb
Version: 2.2.8.0
Summary: Extensions and plugins for OpenSesame to run experiments in a browser using OSWeb
License: COPYING
License-File: COPYING
Author: Sebastiaan Mathôt
Author-email: s.mathot@cogsci.nl
Classifier: License :: Other/Proprietary License
Classifier: Programming Language :: Python :: 2
Classifier: Programming Language :: Python :: 2.7
Classifier: Programming Language :: Python :: 3
Classifier: Programming Language :: Python :: 3.4
Classifier: Programming Language :: Python :: 3.5
Classifier: Programming Language :: Python :: 3.6
Classifier: Programming Language :: Python :: 3.7
Classifier: Programming Language :: Python :: 3.8
Classifier: Programming Language :: Python :: 3.9
Classifier: Programming Language :: Python :: 3.10
Classifier: Programming Language :: Python :: 3.11
Classifier: Programming Language :: Python :: 3.12
Classifier: Programming Language :: Python :: 3.13
Classifier: Programming Language :: Python :: 3.14
Requires-Dist: beautifulsoup4
Requires-Dist: esprima
Requires-Dist: opensesame-core (>=4.1.0a0)
Requires-Dist: requests-toolbelt
Project-URL: Homepage, https://osdoc.cogsci.nl
Project-URL: Repository, https://github.com/open-cogsci/opensesame-extension-osweb/
